pydamain/__init__.py
pydamain/domain/__init__.py
pydamain/domain/messages/__init__.py
pydamain/domain/messages/base.py
pydamain/domain/models/__init__.py
pydamain/domain/models/aggregate.py
pydamain/domain/models/entity.py
pydamain/domain/models/value_object.py
pydamain/domain/service/__init__.py
pydamain/port/__init__.py
pydamain/port/email_sender.py
pydamain/port/outbox.py
pydamain/port/repository.py
pydamain/port/unit_of_work.py
pydamain/service/__init__.py
pydamain/service/handler.py
pydamain/service/message_bus.py
pydamain/service/message_catcher.py
pydamain-0.7.4.dist-info/LICENSE
pydamain-0.7.4.dist-info/WHEEL
pydamain-0.7.4.dist-info/METADATA
pydamain-0.7.4.dist-info/RECORD
